sbireport/__init__.py
sbireport/calculators.py
sbireport/trades.py
sbireport-0.0.2.dist-info/LICENSE
sbireport-0.0.2.dist-info/METADATA
sbireport-0.0.2.dist-info/WHEEL
sbireport-0.0.2.dist-info/top_level.txt
sbireport-0.0.2.dist-info/RECORD
