Metadata-Version: 2.1
Name: sbireport
Version: 0.0.2
Summary: A package to parse Sberbank Investor html reports
Home-page: https://github.com/neverbreaks/sbi-report
Author: shurajan
Author-email: neverbreaks2020@gmail.com
License: UNKNOWN
Platform: UNKNOWN
Classifier: Programming Language :: Python :: 3.8
Classifier: License :: OSI Approved :: MIT License
Requires-Dist: pandas (>=1.1.4)
Requires-Dist: beautifulsoup4 (>=4.9.3)
Requires-Dist: XlsxWriter (>=1.3.7)
